red_val/__init__.py
red_val/exceptions.py
red_val/parsing.py
red_val/red_types.py
red_val/red_validation.py
red_val/red_variables.py
red_val/schemas/__init__.py
red_val/schemas/cli.py
red_val/schemas/connector.py
red_val/schemas/engine.py
red_val/schemas/red.py
red_val/version.py
red_val-9.3.0.dist-info/LICENSE
red_val-9.3.0.dist-info/METADATA
red_val-9.3.0.dist-info/WHEEL
red_val-9.3.0.dist-info/RECORD
