Metadata-Version: 2.1
Name: red-val
Version: 9.3.0
Summary: RED-val is part of the Curious Containers project. It provides functionality to implement red clients and red execution engines.
Home-page: https://www.curious-containers.cc/
License: LGPL-3.0
Author: Christoph Jansen
Author-email: Christoph.Jansen@htw-berlin.de
Requires-Python: >=3.7,<4.0
Classifier: License :: OSI Approved :: GNU Lesser General Public License v3 (LGPLv3)
Classifier: Programming Language :: Python :: 3
Classifier: Programming Language :: Python :: 3.7
Classifier: Programming Language :: Python :: 3.8
Classifier: Programming Language :: Python :: 3.9
Classifier: Programming Language :: Python :: 3.10
Classifier: Programming Language :: Python :: 3.11
Requires-Dist: jsonschema (>=4.12,<5.0)
Project-URL: Repository, https://github.com/curious-containers/curious-containers
